amqppy/__init__.py
amqppy/consumer.py
amqppy/publisher.py
amqppy/utils.py
amqppy-0.0.19.dist-info/zip-safe
amqppy-0.0.19.dist-info/top_level.txt
amqppy-0.0.19.dist-info/METADATA
amqppy-0.0.19.dist-info/DESCRIPTION.rst
amqppy-0.0.19.dist-info/metadata.json
amqppy-0.0.19.dist-info/WHEEL
amqppy-0.0.19.dist-info/RECORD
